subdomaindetectorlive.py
subdomaindetectorstatus-1.0.4.dist-info/LICENSE
subdomaindetectorstatus-1.0.4.dist-info/METADATA
subdomaindetectorstatus-1.0.4.dist-info/WHEEL
subdomaindetectorstatus-1.0.4.dist-info/top_level.txt
subdomaindetectorstatus-1.0.4.dist-info/RECORD
