Metadata-Version: 2.1
Name: subdomaindetectorstatus
Version: 1.0.4
Summary: This tools is used to bruteforce all the subdomain of the domain and filterout the live sites into domain folder
Author: Hariharan C
Requires-Python: >=3.6
License-File: LICENSE
